aiohttp_asyncmdnsresolver/__init__.py
aiohttp_asyncmdnsresolver/_impl.py
aiohttp_asyncmdnsresolver/api.py
aiohttp_asyncmdnsresolver/py.typed
aiohttp_asyncmdnsresolver-0.1.0.dist-info/LICENSE
aiohttp_asyncmdnsresolver-0.1.0.dist-info/METADATA
aiohttp_asyncmdnsresolver-0.1.0.dist-info/WHEEL
aiohttp_asyncmdnsresolver-0.1.0.dist-info/top_level.txt
aiohttp_asyncmdnsresolver-0.1.0.dist-info/RECORD
