Metadata-Version: 2.2
Name: aiohttp-asyncmdnsresolver
Version: 0.1.0
Summary: An async resolver for aiohttp that supports MDNS
License: 
Project-URL: Homepage, https://github.com/aio-libs/aiohttp-asyncmdnsresolver
Project-URL: Issues, https://github.com/aio-libs/aiohttp-asyncmdnsresolver/issues
Classifier: Programming Language :: Python
Classifier: Programming Language :: Python :: 3
Classifier: License :: OSI Approved :: Apache Software License
Classifier: Operating System :: OS Independent
Classifier: Intended Audience :: Developers
Classifier: Topic :: Internet :: WWW/HTTP
Classifier: Framework :: AsyncIO
Classifier: Framework :: aiohttp
Classifier: Development Status :: 5 - Production/Stable
Requires-Python: >=3.9
License-File: LICENSE
Requires-Dist: aiodns>=3.2.0
Requires-Dist: aiohttp>=3.10.0
Requires-Dist: zeroconf>=0.142.0
